pepperboard/__init__.py
pepperboard/core/__init__.py
pepperboard/dashboards/__init__.py
pepperboard/dashboards/dellwarranty.py
pepperboard/dashboards/highstates.py
pepperboard/dashboards/mgrains.py
pepperboard/dashboards/upgrades.py
pepperboard-3.0.data/scripts/pepperboard
pepperboard-3.0.dist-info/LICENSE
pepperboard-3.0.dist-info/METADATA
pepperboard-3.0.dist-info/WHEEL
pepperboard-3.0.dist-info/top_level.txt
pepperboard-3.0.dist-info/RECORD
