Metadata-Version: 2.1
Name: pepperboard
Version: 3.0
Summary: Simple and modular dashboard toolkit for SaltStack
Home-page: https://github.com/webedia-dev/pepperboard
Author: Cyril LAVIER
Author-email: cyril.lavier@webedia-group.com
License: Apache
Download-URL: https://github.com/webedia-dev/pepperboard/releases/tag/v3.0
Platform: UNKNOWN
Classifier: Development Status :: 5 - Production/Stable
Classifier: Intended Audience :: System Administrators
Classifier: Natural Language :: English
Classifier: Programming Language :: Python :: 3
Classifier: Programming Language :: Python :: 3.5
Classifier: License :: OSI Approved :: Apache Software License
Classifier: Topic :: System :: Monitoring
Requires-Dist: psutil
Requires-Dist: salt
